<?xml version="1.0" encoding="utf-8"?>
<CityStati>
  <Status Pool="190130">
    <Requirement ID="">
      <EN>0 Attractiveness</EN>
      <DE>0 Attraktivität</DE>
      <Icon />
    </Requirement>
    <Text ID="11674">
      <EN>Ordinary, as in, a bachelor with a 'fine personality'.</EN>
      <DE>So außergewöhnlich, wie etwas Gewöhnliches eben sein kann.</DE>
      <Icon />
    </Text>
  </Status>
  <Status Pool="193374">
    <Requirement ID="">
      <EN>100 Attractiveness</EN>
      <DE>100 Attraktivität</DE>
      <Icon />
    </Requirement>
    <Text ID="11675">
      <EN>A place at least one person doesn't absolutely hate.</EN>
      <DE>Ein Ort, den man nicht zwangsläufig hassen muss.</DE>
      <Icon />
    </Text>
  </Status>
  <Status Pool="193375">
    <Requirement ID="">
      <EN>250 Attractiveness</EN>
      <DE>250 Attraktivität</DE>
      <Icon />
    </Requirement>
    <Text ID="11676">
      <EN>Nice enough while still remaining deeply weird.</EN>
      <DE>Wirklich nett, wenn auch auf höchst sonderbare Art und Weise.</DE>
      <Icon />
    </Text>
  </Status>
  <Status Pool="190131">
    <Requirement ID="">
      <EN>450 Attractiveness</EN>
      <DE>450 Attraktivität</DE>
      <Icon />
    </Requirement>
    <Text ID="11677">
      <EN>Peculiarity can be attractive.</EN>
      <DE>Eigentümlichkeit kann in manchen Fällen auch anziehend wirken.</DE>
      <Icon />
    </Text>
  </Status>
  <Status Pool="193376">
    <Requirement ID="">
      <EN>700 Attractiveness</EN>
      <DE>700 Attraktivität</DE>
      <Icon />
    </Requirement>
    <Text ID="11679">
      <EN>Pleasant? Now we're getting somewhere.</EN>
      <DE>Gefällig kommt von Gefallen.</DE>
      <Icon />
    </Text>
  </Status>
  <Status Pool="190132">
    <Requirement ID="">
      <EN>1000 Attractiveness</EN>
      <DE>1000 Attraktivität</DE>
      <Icon />
    </Requirement>
    <Text ID="11681">
      <EN>As well-groomed and presented as a prize cow.</EN>
      <DE>Diese Modellstadt ist weniger attraktiv im herkömmlichen Sinne, besitzt aber eine gewisse Vorbildhaftigkeit.</DE>
      <Icon />
    </Text>
  </Status>
  <Status Pool="193377">
    <Requirement ID="">
      <EN>1350 Attractiveness</EN>
      <DE>1350 Attraktivität</DE>
      <Icon />
    </Requirement>
    <Text ID="11684">
      <EN>Scenery that beckons like a siren's song.</EN>
      <DE>Eine Kulisse so anlockend wie der Gesang der Sirenen.</DE>
      <Icon />
    </Text>
  </Status>
  <Status Pool="190133">
    <Requirement ID="">
      <EN>1750 Attractiveness</EN>
      <DE>1750 Attraktivität</DE>
      <Icon />
    </Requirement>
    <Text ID="11682">
      <EN>Something about this place stirs people up. Don't ask me what that means.</EN>
      <DE>Schönheit liegt manchmal im Auge des Betrachters, hier jedoch nicht.</DE>
      <Icon />
    </Text>
  </Status>
  <Status Pool="190409">
    <Requirement ID="">
      <EN>2200 Attractiveness</EN>
      <DE>2200 Attraktivität</DE>
      <Icon />
    </Requirement>
    <Text ID="11688">
      <EN>As pretty as a postcard and redolent of all the fond memories you'd expect to follow.</EN>
      <DE>Wie eine hübsche Postkarte und voller Erinnerungen, denen man nur zu gerne nachhängt.</DE>
      <Icon />
    </Text>
  </Status>
  <Status Pool="193373">
    <Requirement ID="">
      <EN>2700 Attractiveness</EN>
      <DE>2700 Attraktivität</DE>
      <Icon />
    </Requirement>
    <Text ID="11686">
      <EN>Pretty, like bright balloons, riverbanks and calligraphy.</EN>
      <DE>Amutig wie eine holde Maid, die am Flussufer ihr seidenes Haar kämmt.</DE>
      <Icon />
    </Text>
  </Status>
  <Status Pool="193379">
    <Requirement ID="">
      <EN>3250 Attractiveness</EN>
      <DE>3250 Attraktivität</DE>
      <Icon />
    </Requirement>
    <Text ID="11690">
      <EN>So wonderful, it has cheeky scamps skipping down the streets with dripping ices.</EN>
      <DE>Einfach wundervoll hier, all die frechen, kleinen Strolche, die mit bunten Ballons durch die Straßen hüpfen.</DE>
      <Icon />
    </Text>
  </Status>
  <Status Pool="193380">
    <Requirement ID="">
      <EN>3850 Attractiveness</EN>
      <DE>3850 Attraktivität</DE>
      <Icon />
    </Requirement>
    <Text ID="11691">
      <EN>A very serious and grave kind of attractiveness that touches the soul.</EN>
      <DE>Die Art von Schönheit, die es vermag, die Seele zu berühren.</DE>
      <Icon />
    </Text>
  </Status>
  <Status Pool="193381">
    <Requirement ID="">
      <EN>4500 Attractiveness</EN>
      <DE>4500 Attraktivität</DE>
      <Icon />
    </Requirement>
    <Text ID="11694">
      <EN>The kind of place you might expect dresses of the highest feasible circumference.</EN>
      <DE>Man ist wie geblendet von so viel Anmut und Schönheit.</DE>
      <Icon />
    </Text>
  </Status>
  <Status Pool="193382">
    <Requirement ID="">
      <EN>5200 Attractiveness</EN>
      <DE>5200 Attraktivität</DE>
      <Icon />
    </Requirement>
    <Text ID="11696">
      <EN>A flawless, ineffable beauty. Like moondust settled upon ice shards.</EN>
      <DE>Eine außerweltliche, unbeschreibliche Schönheit. Wie Mondstaub, der sich auf Eiszapfen abgelegt hat.</DE>
      <Icon />
    </Text>
  </Status>
  <Status Pool="193383">
    <Requirement ID="">
      <EN>5950 Attractiveness</EN>
      <DE>5950 Attraktivität</DE>
      <Icon />
    </Requirement>
    <Text ID="11697">
      <EN>Sumptuous in its sprawl, elegant in its limbs, this city is one of glossy celebrity.</EN>
      <DE>Die ganze Welt blickt ehrfürchtig auf diesen makellosen Ort.</DE>
      <Icon />
    </Text>
  </Status>
  <Status Pool="193384">
    <Requirement ID="">
      <EN>6500 Attractiveness</EN>
      <DE>6500 Attraktivität</DE>
      <Icon />
    </Requirement>
    <Text ID="11698">
      <EN>Notoriously, deliriously beautiful in the most ambitious conceivable way.</EN>
      <DE>Wären hier die Straßen aus Gold, würde es niemanden verwundern.</DE>
      <Icon />
    </Text>
  </Status>
  <Status Pool="191314">
    <Requirement ID="190650">
      <EN>Mme. Elise "The Nose" Bouquet</EN>
      <DE>Mme. Elise „die Nase“ Bouquet</DE>
      <Icon>
        <Filename>data/ui/2kimages/main/3dicons/specialists/systemic/icon_sommelier_824.png</Filename>
      </Icon>
    </Requirement>
  </Status>
  <Status Pool="191510">
    <Requirement ID="191145">
      <EN>New World Huaca Exhibition</EN>
      <DE>Ausstellung: Huaca in der Neuen Welt</DE>
      <Icon>
        <Filename>data/ui/2kimages/main/3dicons/museum/icon_mummy_nazcan.png</Filename>
      </Icon>
    </Requirement>
  </Status>
</CityStati>