<?xml version="1.0" encoding="utf-8"?>
<ThirdParties>
  <TP ID="73" N="Third_party_03 (Anne Harlow)">
    <T ID="73" I="data/ui/2kimages/main/profiles/3rd_party_03.png" />
    <OI>
      <OI P="EarlyGame" I="190354">
        <PD ID="-6">
          <AI ID="64127250" I="data/ui/2kimages/main/3dicons/resident/icon_resident_farmer.png" />
        </PD>
      </OI>
      <OI P="EarlyMidGame" I="190355">
        <PD ID="-7">
          <AI ID="1952258737" I="data/ui/2kimages/main/3dicons/resident/icon_resident_worker.png" />
        </PD>
      </OI>
      <OI P="MidGame" I="190356">
        <PD ID="-8">
          <AI ID="-105542539" I="data/ui/2kimages/main/3dicons/resident/icon_resident_artisan.png" />
        </PD>
      </OI>
      <OI P="LateMidGame" I="190357">
        <PD ID="-9">
          <AI ID="262583778" I="data/ui/2kimages/main/3dicons/resident/icon_resident_engineer.png" />
        </PD>
      </OI>
      <OI P="LateGame" I="190358">
        <PD ID="-10">
          <AI ID="1655175964" I="data/ui/2kimages/main/3dicons/resident/icon_resident_investor.png" />
        </PD>
      </OI>
      <OI P="EndGame" I="192070">
        <PD ID="-11">
          <AI ID="-910786917" />
        </PD>
      </OI>
    </OI>
  </TP>
  <TP ID="45" N="Third_party_02 (Archibald Blake)">
    <T ID="45" I="data/ui/2kimages/main/profiles/3rd_party_02.png" />
    <OI>
      <OI P="EarlyGame" I="190162">
        <PD ID="-6">
          <AI ID="64127250" I="data/ui/2kimages/main/3dicons/resident/icon_resident_farmer.png" />
        </PD>
      </OI>
      <OI P="EarlyMidGame" I="190163">
        <PD ID="-7">
          <AI ID="1952258737" I="data/ui/2kimages/main/3dicons/resident/icon_resident_worker.png" />
        </PD>
      </OI>
      <OI P="MidGame" I="190164">
        <PD ID="-8">
          <AI ID="-105542539" I="data/ui/2kimages/main/3dicons/resident/icon_resident_artisan.png" />
        </PD>
      </OI>
      <OI P="LateMidGame" I="190165">
        <PD ID="-9">
          <AI ID="262583778" I="data/ui/2kimages/main/3dicons/resident/icon_resident_engineer.png" />
        </PD>
      </OI>
      <OI P="LateGame" I="190166">
        <PD ID="-10">
          <AI ID="1655175964" I="data/ui/2kimages/main/3dicons/resident/icon_resident_investor.png" />
        </PD>
      </OI>
      <OI P="EndGame" I="192069">
        <PD ID="-11">
          <AI ID="-910786917" />
        </PD>
      </OI>
    </OI>
  </TP>
  <TP ID="29" N="Third_party_05 (Isabel Sarmento)">
    <T ID="29" I="data/ui/2kimages/main/profiles/3rd_party_05.png" />
    <OI>
      <OI P="EarlyGame" I="190362">
        <PD ID="-6">
          <AI ID="64127250" I="data/ui/2kimages/main/3dicons/resident/icon_resident_farmer.png" />
        </PD>
      </OI>
      <OI P="EarlyMidGame" I="190362">
        <PD ID="-7">
          <AI ID="1952258737" I="data/ui/2kimages/main/3dicons/resident/icon_resident_worker.png" />
        </PD>
      </OI>
      <OI P="MidGame" I="190362">
        <PD ID="-8">
          <AI ID="-105542539" I="data/ui/2kimages/main/3dicons/resident/icon_resident_artisan.png" />
        </PD>
      </OI>
      <OI P="LateMidGame" I="190363">
        <PD ID="-9">
          <AI ID="262583778" I="data/ui/2kimages/main/3dicons/resident/icon_resident_engineer.png" />
        </PD>
      </OI>
      <OI P="LateGame" I="192072">
        <PD ID="-10">
          <AI ID="1655175964" I="data/ui/2kimages/main/3dicons/resident/icon_resident_investor.png" />
        </PD>
      </OI>
      <OI P="EndGame" I="192073">
        <PD ID="-11">
          <AI ID="-910786917" />
        </PD>
      </OI>
    </OI>
  </TP>
  <TP ID="76" N="Third_party_04 (La Fortune)">
    <T ID="76" I="data/ui/2kimages/main/profiles/3rd_party_04.png" />
    <OI>
      <OI P="EarlyGame">
        <PD ID="-6">
          <AI ID="64127250" I="data/ui/2kimages/main/3dicons/resident/icon_resident_farmer.png" />
        </PD>
      </OI>
      <OI P="EarlyMidGame">
        <PD ID="-7">
          <AI ID="1952258737" I="data/ui/2kimages/main/3dicons/resident/icon_resident_worker.png" />
        </PD>
      </OI>
      <OI P="MidGame" I="192065">
        <PD ID="-8">
          <AI ID="-105542539" I="data/ui/2kimages/main/3dicons/resident/icon_resident_artisan.png" />
        </PD>
      </OI>
      <OI P="LateMidGame" I="192066">
        <PD ID="-9">
          <AI ID="262583778" I="data/ui/2kimages/main/3dicons/resident/icon_resident_engineer.png" />
        </PD>
      </OI>
      <OI P="LateGame" I="192067">
        <PD ID="-10">
          <AI ID="1655175964" I="data/ui/2kimages/main/3dicons/resident/icon_resident_investor.png" />
        </PD>
      </OI>
      <OI P="EndGame" I="192071">
        <PD ID="-11">
          <AI ID="-910786917" />
        </PD>
      </OI>
    </OI>
  </TP>
  <TP ID="46" N="Third_party_07 (Eli Bleakworth)">
    <T ID="46" I="data/ui/2kimages/main/profiles/3rd_party_07.png" />
    <OI>
      <OI P="EarlyGame" I="190167">
        <PD ID="-6">
          <AI ID="64127250" I="data/ui/2kimages/main/3dicons/resident/icon_resident_farmer.png" />
        </PD>
      </OI>
      <OI P="EarlyMidGame" I="190168">
        <PD ID="-7">
          <AI ID="1952258737" I="data/ui/2kimages/main/3dicons/resident/icon_resident_worker.png" />
        </PD>
      </OI>
      <OI P="MidGame" I="190304">
        <PD ID="-8">
          <AI ID="-105542539" I="data/ui/2kimages/main/3dicons/resident/icon_resident_artisan.png" />
        </PD>
      </OI>
      <OI P="LateMidGame" I="190305">
        <PD ID="-9">
          <AI ID="262583778" I="data/ui/2kimages/main/3dicons/resident/icon_resident_engineer.png" />
        </PD>
      </OI>
      <OI P="LateGame" I="190306">
        <PD ID="-10">
          <AI ID="1655175964" I="data/ui/2kimages/main/3dicons/resident/icon_resident_investor.png" />
        </PD>
      </OI>
      <OI P="EndGame" I="190774">
        <PD ID="-11">
          <AI ID="-910786917" />
        </PD>
      </OI>
    </OI>
  </TP>
  <TP ID="78" N="Third_party_08 (Madame Kahina)">
    <T ID="78" I="data/ui/2kimages/main/profiles/3rd_party_08.png" />
    <OI>
      <OI P="EarlyGame" I="190554">
        <PD ID="-6">
          <AI ID="64127250" I="data/ui/2kimages/main/3dicons/resident/icon_resident_farmer.png" />
        </PD>
      </OI>
      <OI P="EarlyMidGame" I="190555">
        <PD ID="-7">
          <AI ID="1952258737" I="data/ui/2kimages/main/3dicons/resident/icon_resident_worker.png" />
        </PD>
      </OI>
      <OI P="MidGame" I="190556">
        <PD ID="-8">
          <AI ID="-105542539" I="data/ui/2kimages/main/3dicons/resident/icon_resident_artisan.png" />
        </PD>
      </OI>
      <OI P="LateMidGame" I="190367">
        <PD ID="-9">
          <AI ID="262583778" I="data/ui/2kimages/main/3dicons/resident/icon_resident_engineer.png" />
        </PD>
      </OI>
      <OI P="LateGame" I="190387">
        <PD ID="-10">
          <AI ID="1655175964" I="data/ui/2kimages/main/3dicons/resident/icon_resident_investor.png" />
        </PD>
      </OI>
      <OI P="EndGame" I="192068">
        <PD ID="-11">
          <AI ID="-910786917" />
        </PD>
      </OI>
    </OI>
  </TP>
  <TP ID="237" N="Third_party_11 (Inuit)">
    <T ID="237" I="data/ui/2kimages/main/profiles/inuit_trader.png" />
    <OI>
      <OI P="EarlyGame" I="193830">
        <PD ID="-6">
          <AI ID="64127250" I="data/ui/2kimages/main/3dicons/resident/icon_resident_farmer.png" />
        </PD>
      </OI>
      <OI P="EarlyMidGame" I="193831">
        <PD ID="-7">
          <AI ID="1952258737" I="data/ui/2kimages/main/3dicons/resident/icon_resident_worker.png" />
        </PD>
      </OI>
      <OI P="MidGame" I="193832">
        <PD ID="-8">
          <AI ID="-105542539" I="data/ui/2kimages/main/3dicons/resident/icon_resident_artisan.png" />
        </PD>
      </OI>
      <OI P="LateMidGame" I="193833">
        <PD ID="-9">
          <AI ID="262583778" I="data/ui/2kimages/main/3dicons/resident/icon_resident_engineer.png" />
        </PD>
      </OI>
      <OI P="LateGame" I="193834">
        <PD ID="-10">
          <AI ID="1655175964" I="data/ui/2kimages/main/3dicons/resident/icon_resident_investor.png" />
        </PD>
      </OI>
      <OI P="EndGame" I="193835">
        <PD ID="-11">
          <AI ID="-910786917" />
        </PD>
      </OI>
    </OI>
  </TP>
  <TP ID="119051" N="Third_party_13 (Emperor Ketema)">
    <T ID="119051" I="data/ui/2kimages/main/profiles/3rd_party_13.png" />
    <OI>
      <OI P="EarlyGame" I="127466">
        <PD ID="-6">
          <AI ID="64127250" I="data/ui/2kimages/main/3dicons/resident/icon_resident_farmer.png" />
        </PD>
      </OI>
      <OI P="EarlyMidGame" I="127476">
        <PD ID="-7">
          <AI ID="1952258737" I="data/ui/2kimages/main/3dicons/resident/icon_resident_worker.png" />
        </PD>
      </OI>
      <OI P="MidGame" I="127477">
        <PD ID="-8">
          <AI ID="-105542539" I="data/ui/2kimages/main/3dicons/resident/icon_resident_artisan.png" />
        </PD>
      </OI>
      <OI P="LateMidGame" I="127478">
        <PD ID="-9">
          <AI ID="262583778" I="data/ui/2kimages/main/3dicons/resident/icon_resident_engineer.png" />
        </PD>
      </OI>
      <OI P="LateGame" I="127479">
        <PD ID="-10">
          <AI ID="1655175964" I="data/ui/2kimages/main/3dicons/resident/icon_resident_investor.png" />
        </PD>
      </OI>
      <OI P="EndGame" I="127480">
        <PD ID="-11">
          <AI ID="-910786917" />
        </PD>
      </OI>
    </OI>
  </TP>
  <TP ID="220" N="Second_ai_11 (Hugo Mercier)">
    <T ID="220" I="data/ui/2kimages/main/profiles/ai_11.png" />
    <OI>
      <OI P="EarlyGame" I="193322">
        <PD ID="-6">
          <AI ID="64127250" I="data/ui/2kimages/main/3dicons/resident/icon_resident_farmer.png" />
        </PD>
      </OI>
      <OI P="EarlyMidGame" I="193323">
        <PD ID="-7">
          <AI ID="1952258737" I="data/ui/2kimages/main/3dicons/resident/icon_resident_worker.png" />
        </PD>
      </OI>
      <OI P="MidGame" I="193324">
        <PD ID="-8">
          <AI ID="-105542539" I="data/ui/2kimages/main/3dicons/resident/icon_resident_artisan.png" />
        </PD>
      </OI>
      <OI P="LateMidGame" I="193325">
        <PD ID="-9">
          <AI ID="262583778" I="data/ui/2kimages/main/3dicons/resident/icon_resident_engineer.png" />
        </PD>
      </OI>
      <OI P="LateGame" I="193326">
        <PD ID="-10">
          <AI ID="1655175964" I="data/ui/2kimages/main/3dicons/resident/icon_resident_investor.png" />
        </PD>
      </OI>
      <OI P="EndGame" I="193327">
        <PD ID="-11">
          <AI ID="-910786917" />
        </PD>
      </OI>
    </OI>
  </TP>
  <TP ID="77" N="Third_party_06 (Old Nate)">
    <T ID="77" I="data/ui/2kimages/main/profiles/3rd_party_06.png" />
    <OI>
      <OI P="EarlyGame" I="193447">
        <PD ID="-6">
          <AI ID="64127250" I="data/ui/2kimages/main/3dicons/resident/icon_resident_farmer.png" />
        </PD>
      </OI>
      <OI P="EarlyMidGame" I="193448">
        <PD ID="-7">
          <AI ID="1952258737" I="data/ui/2kimages/main/3dicons/resident/icon_resident_worker.png" />
        </PD>
      </OI>
      <OI P="MidGame" I="193449">
        <PD ID="-8">
          <AI ID="-105542539" I="data/ui/2kimages/main/3dicons/resident/icon_resident_artisan.png" />
        </PD>
      </OI>
      <OI P="LateMidGame" I="193450">
        <PD ID="-9">
          <AI ID="262583778" I="data/ui/2kimages/main/3dicons/resident/icon_resident_engineer.png" />
        </PD>
      </OI>
      <OI P="LateGame" I="193451">
        <PD ID="-10">
          <AI ID="1655175964" I="data/ui/2kimages/main/3dicons/resident/icon_resident_investor.png" />
        </PD>
      </OI>
      <OI P="EndGame" I="193452">
        <PD ID="-11">
          <AI ID="-910786917" />
        </PD>
      </OI>
    </OI>
  </TP>
</ThirdParties>