<?xml version="1.0" encoding="utf-8"?>
<WorkAreaRiverBuilding>
  <Asset ID="120273" RV="Update 09" RT="Common">
    <N>river_colony02_02_workarea (Paper Mill)</N>
    <T ID="120273" />
    <R ID="118002" />
    <IT>Building</IT>
    <AR ID="22146" />
    <GU />
    <TP />
    <HF />
  </Asset>
  <Asset ID="120274" RV="Update 09" RT="Common">
    <N>river_colony02_01_workarea (Clay Harvester)</N>
    <T ID="120274" />
    <R ID="118002" />
    <IT>Building</IT>
    <AR ID="22146" />
    <GU />
    <TP />
    <HF />
  </Asset>
  <Asset ID="120271" RV="Update 09" RT="Common">
    <N>river_colony02_03_workarea (Water Pump)</N>
    <T ID="120271" />
    <R ID="118002" />
    <IT>Building</IT>
    <AR ID="22146" />
    <GU />
    <TP />
    <HF />
  </Asset>
</WorkAreaRiverBuilding>